date_offset/__init__.py
date_offset/date_offset.py
date_offset/monthdelta.py
date_offset/tests.py
date_offset-0.0.1.dist-info/LICENSE
date_offset-0.0.1.dist-info/METADATA
date_offset-0.0.1.dist-info/WHEEL
date_offset-0.0.1.dist-info/top_level.txt
date_offset-0.0.1.dist-info/RECORD
