Metadata-Version: 2.1
Name: date-offset
Version: 0.0.1
Summary: An library to allow offset of dates by a string
Home-page: https://github.com/django-advance-utils/date-offset
Author: Tom Turner
License: UNKNOWN
Platform: UNKNOWN
Classifier: Programming Language :: Python :: 3
Classifier: License :: OSI Approved :: MIT License
Classifier: Operating System :: OS Independent
Requires-Python: >=3.6
